{
  "department": "lakshmi",
  "scope": "internal",
  "timestamp": "2025-12-18T06:00:12.416342+00:00",
  "query": "Latest trends in fintech, payment processing, and financial analytics in the last 24 hours",
  "raw_intelligence": "Key short answer: In the last 24 hours, public reporting and sector analysis show continued acceleration of three linked themes: rapid deployment of AI/real\u2011time analytics across payments and compliance, expansion of real\u2011time/payment\u2011streaming and embedded finance architectures, and increased regulatory focus on stablecoins/digital\u2011asset payment rails and compliance automation[1][4][6][5].\n\nSupporting details\n\n- AI and real\u2011time analytics driving product and risk changes: Several industry pieces note widespread adoption of AI to automate compliance, underwriting, fraud detection, and analytics\u2014shifting firms from periodic batch processes to continuous, real\u2011time monitoring and decisioning[1][4][8]. These sources highlight AI powering both frontline user experiences (instant credit/underwriting) and backend risk controls (fraud and AML automation)[4][9][1].\n\n- Payments: real\u2011time rails, streaming architectures, and instant settlement: Authors and practitioners emphasize migration from batch to event\u2011driven, streaming platforms (Apache Kafka/Flint examples) to support instant payments, real\u2011time fraud detection, and embedded finance use cases like BNPL and contextual credit[4][6]. Analysts also stress decoupled, modular banking architectures to reduce latency and enable fintech integrations[8].\n\n- Embedded finance and instant decisioning: Embedded payments and contextual financial services (instant credit, BNPL, in\u2011session underwriting) are being built on real\u2011time data and identity verification; vendors argue digital identity and programmable spending controls are becoming prerequisites for secure instant flows[4][6].\n\n- RegTech / compliance automation and stablecoins: Recent coverage highlights stronger uptake of RegTech among large organizations, with AI enabling continuous compliance and regulatory intelligence; governments and regulators continue drafting payments/digital\u2011asset rules, including authorizations for tokenised stored\u2011value (stablecoin) facilities\u2014raising compliance and product design imperatives for payment processors and fintechs[1][5].\n\n- Credit and consumer finance trends: For consumer credit, especially Gen Z and Millennials, fintechs are deploying simpler UX, alternative data for fairer credit decisions, continuous credit\u2011monitoring dashboards, and AI scoring to widen inclusion while emphasizing data security and transparency[2][9].\n\n- Market signals and investor focus (equities): Market scanners flagged specific fintech stocks today, indicating investor attention to mortgage/marketplace/payment platform companies and continuing market volatility tied to regulatory and execution risk[3].\n\nWhat this means for practitioners (concise implications)\n- Technical: Prioritize event\u2011streaming, low\u2011latency data platforms and scalable ML infra to enable real\u2011time scoring, fraud rules, and personalization[4][8].  \n- Compliance/product: Build compliance automation (RegTech) into product lifecycles and monitor evolving stablecoin/token rules for payments products[1][5].  \n- Go\u2011to\u2011market: Differentiate via embedded identity, transparent credit UX, and seamless instant settlement to meet consumer and SMB expectations[6][2].\n\nLimits and caveats: The above synthesizes industry articles and analyst posts published in the past 24 hours; these are industry observations and predictions rather than peer\u2011reviewed research, and regulatory positions (especially on stablecoins/token custody) are still evolving across jurisdictions[1][5]. If you want, I can pull the specific articles referenced and summarize key quotes or extract vendor/technology examples for implementation planning.",
  "processed_intelligence": "Key short answer: In the last 24 hours, public reporting and sector analysis show continued acceleration of three linked themes: rapid deployment of AI/real\u2011time analytics across payments and compliance, expansion of real\u2011time/payment\u2011streaming and embedded finance architectures, and increased regulatory focus on stablecoins/digital\u2011asset payment rails and compliance automation[1][4][6][5].\n\nSupporting details\n\n- AI and real\u2011time analytics driving product and risk changes: Several industry pieces note widespread adoption of AI to automate compliance, underwriting, fraud detection, and analytics\u2014shifting firms from periodic batch processes to continuous, real\u2011time monitoring and decisioning[1][4][8]. These sources highlight AI powering both frontline user experiences (instant credit/underwriting) and backend risk controls (fraud and AML automation)[4][9][1].\n\n- Payments: real\u2011time rails, streaming architectures, and instant settlement: Authors and practitioners emphasize migration from batch to event\u2011driven, streaming platforms (Apache Kafka/Flint examples) to support instant payments, real\u2011time fraud detection, and embedded finance use cases like BNPL and contextual credit[4][6]. Analysts also stress decoupled, modular banking architectures to reduce latency and enable fintech integrations[8].\n\n- Embedded finance and instant decisioning: Embedded payments and contextual financial services (instant credit, BNPL, in\u2011session underwriting) are being built on real\u2011time data and identity verification; vendors argue digital identity and programmable spending controls are becoming prerequisites for secure instant flows[4][6].\n\n- RegTech / compliance automation and stablecoins: Recent coverage highlights stronger uptake of RegTech among large organizations, with AI enabling continuous compliance and regulatory intelligence; governments and regulators continue drafting payments/digital\u2011asset rules, including authorizations for tokenised stored\u2011value (stablecoin) facilities\u2014raising compliance and product design imperatives for payment processors and fintechs[1][5].\n\n- Credit and consumer finance trends: For consumer credit, especially Gen Z and Millennials, fintechs are deploying simpler UX, alternative data for fairer credit decisions, continuous credit\u2011monitoring dashboards, and AI scoring to widen inclusion while emphasizing data security and transparency[2][9].\n\n- Market signals and investor focus (equities): Market scanners flagged specific fintech stocks today, indicating investor attention to mortgage/marketplace/payment platform companies and continuing market volatility tied to regulatory and execution risk[3].\n\nWhat this means for practitioners (concise implications)\n- Technical: Prioritize event\u2011streaming, low\u2011latency data platforms and scalable ML infra to enable real\u2011time scoring, fraud rules, and personalization[4][8].  \n- Compliance/product: Build compliance automation (RegTech) into product lifecycles and monitor evolving stablecoin/token rules for payments products[1][5].  \n- Go\u2011to\u2011market: Differentiate via embedded identity, transparent credit UX, and seamless instant settlement to meet consumer and SMB expectations[6][2].\n\nLimits and caveats: The above synthesizes industry articles and analyst posts published in the past 24 hours; these are industry observations and predictions rather than peer\u2011reviewed research, and regulatory positions (especially on stablecoins/token custody) are still evolving across jurisdictions[1][5]. If you want, I can pull the specific articles referenced and summarize key quotes or extract vendor/technology examples for implementation planning.",
  "citations": [
    "https://fintech.global/2025/12/17/the-trends-that-drove-regtech-forward-in-2025/",
    "https://networkustad.com/2025/12/17/fintech-credit-trend-gen-z-millennials/",
    "https://www.marketbeat.com/instant-alerts/fintech-stocks-to-keep-an-eye-on-december-17th-2025-12-17/",
    "https://www.kai-waehner.de/blog/2025/12/17/10-fintech-predictions-that-depend-on-real-time-data-streaming/",
    "https://piperalderman.com.au/financial-services-fintech-2025-year-in-review/",
    "https://blog.vopay.com/fintech-predictions-trends-2026/",
    "https://markets.businessinsider.com/news/currencies/syafiq-wirawan-on-asymmetric-risk-and-fintech-architectures-in-2025-1035653936",
    "https://www.forrester.com/blogs/architecting-agility-decoupled-banking-systems-will-be-the-key-to-success-in-2026/",
    "https://www.fintechweekly.com/magazine/articles/digital-lending-future-effortless-borrowing-online-loans-ai-automation",
    "https://www.mdtmi.com/insights/blog/2025-credit-union-trends-and-lessons/"
  ],
  "model_used": "sonar"
}